Metadata-Version: 1.0
Name: firehoser
Version: 1.0.3
Summary: Command line tool that automates the setup of a lambda function that fowards records from Kinesis to Firehose.
Home-page: https://github.com/bufferapp/firehoser
Author: David Gasquez
Author-email: davidgasquez@buffer.com
License: MIT
Keywords: kinesis aws firehose lambda
Platform: UNKNOWN
